[
  {
    "inputs": [
      {
        "internalType": "address",
        "name": "_token0",
        "type": "address"
      },
      {
        "internalType": "address",
        "name": "_token1",
        "type": "address"
      }
    ],
    "name": "kukuswapPairIsInitialised",
    "outputs": [
      {
        "internalType": "bool",
        "name": "",
        "type": "bool"
      }
    ],
    "stateMutability": "view",
    "type": "function"
  },
  {
    "inputs": [
      {
        "internalType": "contract IERC20",
        "name": "_baseToken",
        "type": "address"
      },
      {
        "internalType": "contract IERC20",
        "name": "_saleToken",
        "type": "address"
      },
      {
        "internalType": "uint256",
        "name": "_baseAmount",
        "type": "uint256"
      },
      {
        "internalType": "uint256",
        "name": "_saleAmount",
        "type": "uint256"
      },
      {
        "internalType": "uint256",
        "name": "_unlock_date",
        "type": "uint256"
      },
      {
        "internalType": "address payable",
        "name": "_withdrawer",
        "type": "address"
      }
    ],
    "name": "lockLiquidity",
    "outputs": [],
    "stateMutability": "nonpayable",
    "type": "function"
  }
]
